buildout.recipe.uwsgi-0.1.2-py3.5-nspkg.pth
buildout/recipe/__init__.py
buildout/recipe/uwsgi.py
buildout.recipe.uwsgi-0.1.2.dist-info/DESCRIPTION.rst
buildout.recipe.uwsgi-0.1.2.dist-info/METADATA
buildout.recipe.uwsgi-0.1.2.dist-info/RECORD
buildout.recipe.uwsgi-0.1.2.dist-info/WHEEL
buildout.recipe.uwsgi-0.1.2.dist-info/entry_points.txt
buildout.recipe.uwsgi-0.1.2.dist-info/metadata.json
buildout.recipe.uwsgi-0.1.2.dist-info/namespace_packages.txt
buildout.recipe.uwsgi-0.1.2.dist-info/top_level.txt
