Metadata-Version: 2.0
Name: buildout.recipe.uwsgi
Version: 0.1.2
Summary: Buildout recipe for downloading, compiling and configuring uWSGI
Home-page: http://github.com/lcosmin/buildout.recipe.uwsgi
Author: Cosmin Luță
Author-email: q4break@gmail.com
License: BSD
Platform: UNKNOWN
Classifier: Programming Language :: Python
Classifier: License :: OSI Approved :: BSD License
Classifier: Development Status :: 4 - Beta
Classifier: Operating System :: OS Independent
Classifier: Framework :: Buildout
Classifier: Intended Audience :: Developers
Classifier: Topic :: Internet :: WWW/HTTP :: Dynamic Content
Requires-Dist: zc.recipe.egg
Requires-Dist: setuptools
